seqlogic/__init__.py
seqlogic/_design.py
seqlogic/_expr.py
seqlogic/_hier.py
seqlogic/_proc_if.py
seqlogic/_trace_if.py
seqlogic/algorithm/__init__.py
seqlogic/algorithm/gray.py
seqlogic/algorithm/addition/__init__.py
seqlogic/algorithm/addition/fa.py
seqlogic/algorithm/addition/ha.py
seqlogic/algorithm/addition/ksa.py
seqlogic/algorithm/addition/rca.py
seqlogic/algorithm/cryptography/__init__.py
seqlogic/algorithm/cryptography/aes.py
seqlogic/check/__init__.py
seqlogic/check/ready_valid.py
seqlogic/control/__init__.py
seqlogic/control/sync.py
seqlogic/datastruct/__init__.py
seqlogic/datastruct/fbeb.py
seqlogic/datastruct/fbeb_ctl.py
seqlogic/datastruct/hbeb.py
seqlogic/datastruct/pipe_reg.py
seqlogic-0.53.0.dist-info/METADATA
seqlogic-0.53.0.dist-info/WHEEL
seqlogic-0.53.0.dist-info/top_level.txt
seqlogic-0.53.0.dist-info/RECORD
