Metadata-Version: 2.4
Name: seqlogic
Version: 0.53.0
Summary: Sequential Logic
Project-URL: Repository, https://github.com/cjdrake/seqlogic.git
Requires-Python: >=3.12
Requires-Dist: bvwx>=0.20.0
Requires-Dist: deltacycle>=0.28.0
Requires-Dist: pyvcd
